happy/__init__.py
happy/main.py
happyjar-4.0.1.dist-info/LICENSE
happyjar-4.0.1.dist-info/METADATA
happyjar-4.0.1.dist-info/WHEEL
happyjar-4.0.1.dist-info/entry_points.txt
happyjar-4.0.1.dist-info/top_level.txt
happyjar-4.0.1.dist-info/RECORD
