Metadata-Version: 2.1
Name: happyjar
Version: 4.0.1
Summary: Keep a happy jar from your terminal
Home-page: https://github.com/TechWiz-3/happy-jar-cli
Author: Zac the Wise aka TechWiz-3
License-File: LICENSE
